colab_assist/__init__.py
colab_assist/_colab.py
colab_assist/colab_assist.py
colab_assist/py.typed
colab_assist-0.2.4.dist-info/METADATA
colab_assist-0.2.4.dist-info/WHEEL
colab_assist-0.2.4.dist-info/licenses/LICENSE
colab_assist-0.2.4.dist-info/RECORD
