Metadata-Version: 2.4
Name: colab-assist
Version: 0.2.4
Summary: Google Colab workflow utilities
Project-URL: Homepage, https://github.com/dd-n-kk/colab-assist
Project-URL: Documentation, https://colab-assist.readthedocs.io
Project-URL: Issues, https://github.com/dd-n-kk/colab-assist/issues
Author-email: dd-n-kk <djlstvn.cs03@gmail.com>
License-File: LICENSE
Keywords: Colab,GitHub,Google,cloud,utilities,uv,workflow
Classifier: Intended Audience :: Developers
Classifier: License :: OSI Approved :: MIT License
Classifier: Programming Language :: Python :: 3
Classifier: Topic :: Utilities
Requires-Python: >=3.11
